e2e.pom-0.1.8-py3.10-nspkg.pth
e2e/pom/__init__.py
e2e/pom/base.py
e2e/pom/components.py
e2e/pom/dom.py
e2e/pom/exceptions.py
e2e/pom/locators.py
e2e/pom/page.py
e2e/pom/py.typed
e2e/pom/types.py
e2e.pom-0.1.8.dist-info/LICENSE
e2e.pom-0.1.8.dist-info/METADATA
e2e.pom-0.1.8.dist-info/WHEEL
e2e.pom-0.1.8.dist-info/namespace_packages.txt
e2e.pom-0.1.8.dist-info/top_level.txt
e2e.pom-0.1.8.dist-info/RECORD
